{
  "author": {
    "name": "Brian Holt",
    "company": "Stripe"
  },
  "title": "A Superb Course",
  "subtitle": "That Teaches Nice Things",
  "frontendMastersLink": "https://frontendmasters.com/courses/complete-react-v6/",
  "social": {
    "linkedin": "btholt",
    "github": "btholt",
    "twitter": "holtbt"
  },
  "description": "A very nice course",
  "keywords": ["a nice course", "for people", "to learn", "nice things"],
  "productionBaseUrl": "http://btholt.github.io/remix-course-starter"
}
